pyQSM/canopy_metrics.py
pyQSM/pyqsm_config.toml
pyQSM/qsm_generation.py
pyQSM/set_config.py
pyQSM/tree_isolation.py
pyQSM/geometry/mesh_processing.py
pyQSM/geometry/point_cloud_processing.py
pyQSM/geometry/reconstruction.py
pyQSM/geometry/skeletonize.py
pyQSM/geometry/zoom.py
pyQSM/math/fit.py
pyQSM/math/math_utils.py
pyQSM/utils/io.py
pyQSM/utils/lib_integration.py
pyQSM/utils/log_utils.py
pyQSM/viz/color.py
pyQSM/viz/plotting.py
pyQSM/viz/ray_casting.py
pyQSM/viz/viz_utils.py
pyqsm-0.1.0.dist-info/licenses/LICENSE
pyqsm-0.1.0.dist-info/METADATA
pyqsm-0.1.0.dist-info/WHEEL
pyqsm-0.1.0.dist-info/entry_points.txt
pyqsm-0.1.0.dist-info/top_level.txt
pyqsm-0.1.0.dist-info/RECORD
