Metadata-Version: 2.4
Name: pyqsm
Version: 0.1.0
Summary: Python Utilities for TLS LiDAR Scans of Trees
Author: pyQSM Contributors
Maintainer: pyQSM Contributors
License: Mozilla Public License Version 2.0
Project-URL: Homepage, https://github.com/wischmcj/pyQSM
Project-URL: Documentation, https://pyqsm.readthedocs.io/
Project-URL: Repository, https://github.com/your-username/pyQSM.git
Project-URL: Issues, https://github.com/your-username/pyQSM/issues
Keywords: lidar,point-cloud,tree-analysis,forestry,3d-processing,skeletonization,qsm,terrestrial-laser-scanning,tls
Classifier: Development Status :: 3 - Alpha
Classifier: Intended Audience :: Science/Research
Classifier: License :: OSI Approved :: Mozilla Public License 2.0 (MPL 2.0)
Classifier: Operating System :: OS Independent
Classifier: Programming Language :: Python :: 3
Classifier: Programming Language :: Python :: 3.8
Classifier: Programming Language :: Python :: 3.9
Classifier: Programming Language :: Python :: 3.10
Classifier: Programming Language :: Python :: 3.11
Classifier: Programming Language :: Python :: 3.12
Classifier: Topic :: Scientific/Engineering
Classifier: Topic :: Scientific/Engineering :: Information Analysis
Classifier: Topic :: Scientific/Engineering :: Mathematics
Requires-Python: >=3.8
License-File: LICENSE
Requires-Dist: open3d>=0.17.0
Requires-Dist: matplotlib>=3.5.0
Requires-Dist: numpy>=1.21.0
Requires-Dist: scipy>=1.7.0
Requires-Dist: polyscope>=1.0.0
Requires-Dist: networkx>=2.6.0
Requires-Dist: mistree>=0.1.0
Requires-Dist: robust-laplacian>=0.1.0
Requires-Dist: plyfile>=0.7.0
Provides-Extra: dev
Requires-Dist: pytest>=6.0.0; extra == "dev"
Requires-Dist: pytest-cov>=2.0.0; extra == "dev"
Requires-Dist: black>=21.0.0; extra == "dev"
Requires-Dist: flake8>=3.8.0; extra == "dev"
Requires-Dist: mypy>=0.910; extra == "dev"
Requires-Dist: pre-commit>=2.0.0; extra == "dev"
Provides-Extra: docs
Requires-Dist: sphinx>=4.0.0; extra == "docs"
Requires-Dist: sphinx-rtd-theme>=1.0.0; extra == "docs"
Requires-Dist: myst-parser>=0.15.0; extra == "docs"
Provides-Extra: all
Requires-Dist: pyqsm[dev,docs]; extra == "all"
Dynamic: license-file
